Workbook
Name No_residencial: tabla!$G$70:$G$121
Name NO_RESIDENCIAL_COND: tabla!$I$70:$I$90
Name NO_RESIDENCIAL_ORD: tabla!$G$70:$G$100
Name RESIDENCIAL: tabla!$E$67:$E$68

Sheet menore
A1: Determinación de cargas urbanísticas y cesiones obligatorias en proyectos con superficies menores a una hectárea.
A4: ASP | B4: Area de Servicio Publico | C4: =((C5*C6)/(C7+C6))*C8*C9 -> 1507.3408 | P4: si
A5: AP | B5: Area total del Predio | C5: 9500 | D5: M2 | E5: Tipo | F5: Q | G5: BASE | H5: AMPLIADO | I5: Final | P5: no | R5: base
A6: EAD | B6: Indice de Edificabilidad | C6: =0.75*I6 -> 1.725 | E6: base | F6: 2 | G6: =LOOKUP(F6,tabla!A4:A11,tabla!B4:B11) -> 2.3 | H6: =LOOKUP(F6,tabla!A4:A11,tabla!C4:C11) -> 3.5 | I6: =IF((E6="ampliado"),H6,G6) -> 2.3 | R6: ampliado
A7: CEU | B7: Equilibrio Urbanistico | C7: 8.875 | P7: Residenciales
A8: FCT | B8: Factor de Reduccion por donacion de area de servicio | C8: =IF(D8="si",0.75,1) -> 0.75 | D8: si
A9: FC-U | B9: Uso de Suelo | C9: =IF((D9="Residenciales"),(1),(IF((D9="Oficinas"),(1.1),IF((D9="No Residenciales"),(1.3),0)))) -> 1.3 | D9: No residenciales | P9: No residenciales
B12: Area Efectiva | C12: =C5-C4 -> 7992.6592 | D12: m2
B13: Sesion de Area vial | C13: 1050 | D13: m2
B14: Area efectiva 2 | C14: =C12-C13 -> 6942.6592 | D14: m2 | E14: %
B15: Area Permeable | C15: =E15*C14 -> 694.26592 | D15: m2 | E15: =LOOKUP(F6,tabla!A4:A11,tabla!E4:E11) -> 0.1
B16: Area permeable Propuesta | C16: 765 | D16: m2
B17: Area efectiva Final | C17: =C14-C15 -> 6248.3933 | D17: m2
B18: Area con factor | C18: =C14*G6 -> 15968.116 | D18: m
B19: Area propuesta | C19: 24708 | D19: m2 | E19: =13800/2.3 -> 6000 | F19: =9500-E19 -> 3500
B20: Area de vivieda | C20: 6000 | D20: m2
B21: % uso residencial | C21: =C20/C19 -> 0.24283633 | D21: % | E21: Si pasa del 30% para uso mixto puede usarse ampliado

Sheet mayores
A1: Determinación de cargas urbanísticas y cesiones obligatorias en proyectos con superficies mayores a una hectárea.
A4: ASP-PP | B4: Area de Servicio Publico | C4: =((C5*C6)/(C7+C6))*C8 -> 1902.2055 | D4: m2 | Q4: si
A5: AP | B5: Area total del Predio | C5: 9500 | D5: m2 | E5: Tipo | F5: Q | G5: BASE | H5: AMPLIADO | I5: Indice sin reducir | Q5: no | S5: base
A6: EAD | B6: Indice de Edificabilidad | C6: =0.75*I6 -> 1.725 | E6: base | F6: 2 | G6: =LOOKUP(F6,tabla!A4:A11,tabla!B4:B11) -> 2.3 | H6: =LOOKUP(F6,tabla!A4:A11,tabla!C4:C11) -> 3.5 | I6: =IF((E6="ampliado"),H6,G6) -> 2.3 | S6: ampliado
A7: CEU | B7: Equilibrio Urbanistico | C7: 6.89 | Q7: Residenciales
A8: FC-U | B8: Uso de Suelo | C8: =IF((D8="Residenciales"),(1),(IF((D8="Oficinas"),(1.1),IF((D8="No Residenciales"),(1.3),0)))) -> 1 | D8: Residenciales | Q8: No residenciales
B13: Area Vial | C13: =C4*0.3 -> 570.66164 | D13: m2
B14: Equipamiento Comunitario Municipal | C14: =0.4*C4 -> 760.88218 | D14: m2
B15: Infraestructura Urbana | C15: =C4*0.3 -> 570.66164 | D15: m2
B19: todas las urbanizaciones entran aquí

Sheet FACTIBILIDAD
C2: BAJO IMPACTO | F2: Vigencia 6 meses a partir de la fecha de emisión
C8: Fecha | D8: =TODAY() -> 46180
C9: Propietario | D9: CAJAS ITZEP, RAFAEL SALVADOR
C10: Direccion | D10: 8va AVENIDA 0-10
C11: Expediente | D11: RPNC1-4240426
C12: Nombre del Proyecto | D12: UNIFAMILIAR
C13: Finca | D13: F
C14: Folio | D14: FOL
C15: Libro | D15: LIB
D17: X | E17: Y
B18: 1 | C18: COORDENADAS GTM
B19: 2 | C19: CLASIFICACION DEL SUELO URBANO | D19: URBANO Q2 (URB-Q2)
B20: 3 | C20: SUELO ESPECIAL DE PROTECCION | D20: N/A
B21: 4 | C21: CLASIFICACION DEL SUELO RURAL Y FORESTAL | D21: N/A
B22: 5 | C22: AREA DE AMENAZA POR SISMO | D22: NO
B23: 6 | C23: AREA DE INUNDACION | D23: NO
B24: 7 | C24: AREA DE AMENAZA POR DESLIZAMIENTO | D24: NO
B25: 8 | C25: AREA SUJETA A PROYECTO URBANO | D25: NO
B26: 9 | C26: SELECCIONAR PROYECTO URBANO | D26: N/A
C27: CENTRO HISTORICO Y/O MONUMENTOS AISLADOS | D27: NO
C28: PLAN PARCIAL | D28: NO
C31: AREA TOTAL DEL PREDIO O PREDIOS DEL PROYECTO | D31: 200
C32: FRENTE DEL PREDIO | D32: 8
C35: AREA DEL PROYECTO NUEVO HUELLA | D35: =+D31 -> 200 | F35: INCLUYE AREA PERMEABLE PROPUESTA
C36: AREAS DE CONSTRUCCIÓN EXISTENTES TODOS LOS NIVELES | D36: 0 | E36: m2 | F36: PARA INDICE DE EDIFICABILIDAD
C37: AREA DE CONSTRUCCION A EJECUTAR SUMATORIA DE TODOS LOS NIVELES SIN INCLUIR SOTANOS (AREAS TECHADAS) | D37: 66666 | E37: m2 | F37: PARA INDICE DE EDIFICABILIDAD CARGA URBANISTICA
C38: AREA PERMEABLE ACTUAL | D38: =+D35 -> 200 | E38: m2 | F38: SI EL PROYECTO ES NUEVO INDICAR AREA TOTAL
C39: AREA PERMEABLE FINAL | D39: 77777 | E39: m2 | F39: REALIZAR CALCULO DE FORMA MANUAL TOMAR EN CUENTA TODO LO CONSTRUIDO
C40: ALTURA DEL EDIFICIO NUEVO | D40: 2.74 | E40: m | F40: ALTURA FINAL
C41: INDICE DE EDIFICABILIDAD DEL PROYECTO | D41: =ROUNDUP($D$37/D35,2) -> 333.33 | F41: INDICE TOMANDO EN CUENTA CONSTRUCCIONES EXISTENTES
C42: INDICE DE EDIFICABILIDAD ACTUAL | D42: =IFERROR(ROUNDUP((D36/D31),2),"") -> 0 | F42: INDICE DE EDIFICABILIDAD ACTUAL
C43: INDICE DE EDIFICABILIDAD PROYECTADO | D43: =IFERROR(((D36+D37)/D31),"") -> 333.33 | F43: INDICE DE EDIFICABILIDAD PROYECTO PARA CARGA URBANISTICA
C44: ALTURA PRIMER BLOQUE | D44: =D40 -> 2.74
C45: ALTURA SEGUNDO BLOQUE | D45: 0
C46: % DE PERMEABILIDAD | D46: =ROUNDUP(D39/D31,2) -> 388.89
F47: Borrar datos para no variar cantidades
C48: AREAS PARA USO DE SUELO MAXIMO Y MIXTURA (INCLUYE SOTANOS) M2 COLOCAR SOLO EL PROYECTO NUEVO
C49: USO DE SUELO 1 | D49: =+D37 -> 66666 | E49: RESIDENCIAL | F49: RESIDENCIAL
C50: USO DE SUELO 2
C51: USO DE SUELO 3
C52: USO DE SUELO 4
D53: =SUM(D49:D52) -> 66666 | E53: m2
C55: RESIDENCIAL | D55: =SUMIF(E49:E52,"RESIDENCIAL",D49:D52) -> 66666
C56: NO RESIDENCIAL ORDINARIO | D56: =SUMIF(E49:E52,"NO_RESIDENCIAL_ORD",D49:D52) -> 0
C57: NO RESINDENCIAL CONDICIONADO | D57: =SUMIF(E49:E52,"NO_RESIDENCIAL_COND",D49:D52) -> 0
C59: MIXTURA NO SE INCLUYEN SOTANOS) | D59: =$D$55/$D$53 -> 1
E60: IE NUEVO
C61: INDICE DE EDIFICABILIDAD USADO | D61: AMPLIADO
C62: CONSTANTE DE EQUILIBRIO URBANISTICO | D62: 8.875 | E62: MAYORES A 1 HECTAREA | F62: 6.89
C63: DONACION A LA MUNICIPALIDAD (SOLO MENORES A 1 HECTAREA) | D63: NO
C65: CESION OBLIGATORIA | D65: =IF($D$35>10000,((($D$35*$D$41)/($F$62+$D$41))*IF($D$59=100%,1,1.3)),(($D$35*($D$41*0.75))/($D$62+($D$41*0.75))*(IF($D$63="NO",1,0.75))*(IF($D$59=100%,1,1.3)))) -> 193.14334
C68: INGRESE JERARQUIZACION DE VIAS | D68: 1 | E68: V3
D69: 2
D70: 3
D71: 4
C73: INGRESE NOMBRE ACTUAL DE LAS CALLES O AVENIDAS DEBE INGRESARSE EN EL ORDEN QUE SE INGRESO LA JERARQUIZACIÓN VIAL | D73: 1
D74: 2
D75: 3
D76: 4
C80: AP

Sheet FORMATO  FACT
G4: CERTIFICACIÓN DE FACTIBILIDAD | L4: FOLIO ___
G6: Vigencia 6 meses a partir de la fecha de emisión
F9: DATOS DEL EXPEDIENTE:
F11: EXPEDIENTE | G11: =FACTIBILIDAD!D11 -> RPNC1-4240426
F12: NOMBRE | G12: =FACTIBILIDAD!D9 -> CAJAS ITZEP, RAFAEL SALVADOR
F13: DIRECCION | G13: =FACTIBILIDAD!D10 -> 8va AVENIDA 0-10
F14: FECHA | G14: =FACTIBILIDAD!D8 -> 46180
F15: NOMBRE DEL PROYECTO | G15: =FACTIBILIDAD!D12 -> UNIFAMILIAR
F16: FINCA | G16: =FACTIBILIDAD!D13 -> F
F17: FOLIO | G17: =FACTIBILIDAD!D14 -> FOL
F18: LIBRO | G18: =FACTIBILIDAD!D15 -> LIB
F20: EVALUACION DEL PROYECTO RESPECTO AL SECTOR:
F22: CLASIFICACIÓN DEL SUELO | G22: =IF(N35="", "NO ESTA SUJETO A CARGAS URBANISTICAS",FACTIBILIDAD!D19) -> URBANO Q2 (URB-Q2)
F24: DATOS DEL SECTOR | I24: DATOS DEL PROYECTO | L24: EVALUACIÓN
F25: AREA MINIMA PREDIO (m2) | G25: =LOOKUP(G22,tabla!G4:G12,tabla!H4:H11) -> 400 | I25: AREA (m2) | J25: =FACTIBILIDAD!D31 -> 200 | L25: =IF(J25<=G25,"NO CUMPLE","SI CUMPLE") -> NO CUMPLE
F26: FRENTE MINIMO (m) | G26: =LOOKUP(FACTIBILIDAD!D19,tabla!G4:G11,tabla!I4:I11) -> 15 | I26: FRENTE (m) | J26: =FACTIBILIDAD!D32 -> 8 | L26: =IF(J26<G26,"NO CUMPLE","SI CUMPLE") -> NO CUMPLE
F27: ALTURA MAXIMA (m) | G27: =LOOKUP(FACTIBILIDAD!D19,tabla!G4:G10,tabla!P4:P11) -> 47 | I27: ALTURA (m) | J27: =FACTIBILIDAD!D40 -> 2.74 | L27: =IF(G27<=J27,"NO CUMPLE","SI CUMPLE") -> SI CUMPLE
F28: ALTURA DEL PRIMER BLOQUE (m) | G28: =LOOKUP(G22,tabla!G4:G12,tabla!M4:M11) -> 18 | I28: ALTURA DEL PRIMER BLOQUE (m) | J28: =FACTIBILIDAD!D44 -> 2.74 | L28: =IF(G28<J28,"NO CUMPLE","SI CUMPLE") -> SI CUMPLE
F29: ALTURA DEL SEGUNDO BLOQUE (m) | G29: =LOOKUP(G22,tabla!G4:G12,tabla!S4:S10) -> 29 | I29: ALTURA DEL SEGUNDO BLOQUE (m) | J29: =FACTIBILIDAD!D45 -> 0 | L29: =IF(G29<J29,"NO CUMPLE","SI CUMPLE") -> SI CUMPLE
F30: PERMEABILIDAD | G30: =LOOKUP(FACTIBILIDAD!D19,tabla!G4:G11,tabla!L4:L11) -> 0.1 | I30: PERMEABILIDAD FINAL | J30: =IF(J25<150,"NO DEBE DEJAR AREA PERMEABLE",FACTIBILIDAD!D39/FACTIBILIDAD!D35) -> 388.885 | L30: =IF(OR(G30<=J30,J30="NO DEBE DEJAR AREA PERMEABLE"),"SI CUMPLE","NO CUMPLE") -> SI CUMPLE
F31: MAXIMO DE M2 NO ORDINARIOS | G31: =LOOKUP('FORMATO FACT'!G22:J22,tabla!G4:G12,tabla!U4:U11) -> 3000 | I31: METROS CUADRADOS | J31: =FACTIBILIDAD!D56 -> 0 | L31: =IF(J31>G31,"NO CUMPLE","SI CUMPLE") -> SI CUMPLE
F32: MAXIMO DE M2 CONDICIONADOS | G32: =LOOKUP('FORMATO FACT'!G22:J22,tabla!G5:G13,tabla!U5:U12) -> 3000 | I32: METROS CUADRADOS | J32: =FACTIBILIDAD!D57 -> 0 | L32: =IF(J32>G32,"NO CUMPLE","SI CUMPLE") -> SI CUMPLE
F33: USO DE SUELO MIXTO (RESIDENCIAL) | G33: =LOOKUP(FACTIBILIDAD!D19,tabla!G4:G11,tabla!T4:T10) -> 0.3 | I33: USO DE SUELO MIXTO (RESIDENCIAL) | J33: =FACTIBILIDAD!D59 -> 1 | L33: =IF(G33<=J33,"SI CUMPLE","NO CUMPLE") -> SI CUMPLE
F34: INDICE DE EDIFICABILIDAD MAX. | G34: =IF((FACTIBILIDAD!D61="AMPLIADO"),(LOOKUP('FORMATO FACT'!G22:J22,tabla!G4:G12,tabla!K4:K12)),IF((FACTIBILIDAD!D61="BASE"),(LOOKUP('FORMATO FACT'!G22:J22,tabla!G4:G12,tabla!J4:J12)),( FACTIBILIDAD!E61))) -> 3.2 | I34: INDICE DE EDIFICABILIDAD | J34: =FACTIBILIDAD!D43 -> 333.33 | L34: =IF(G34<=J34,"NO CUMPLE","SI CUMPLE") -> NO CUMPLE
F35: M2 MAXIMOS A CONSTRUIR EDIFICABILIDAD | G35: =J25*G34 -> 640 | I35: METROS DEL CONSTRUCCION | J35: =FACTIBILIDAD!D37+FACTIBILIDAD!D36 -> 66666 | L35: =IF(J35>G35,"NO CUMPLE","SI CUMPLE") -> NO CUMPLE | N35: =IF(J25<=250,"NO ESTA SUJETO A CARGAS URBANISTICAS"," ") -> NO ESTA SUJETO A CARGAS URBANISTICAS
F37: AREA DE CESION OBLIGATORIA | I37: EVALUACIÓN | L37: AREA DE PROYECTO
F38: DONARA A LA MUNCIPALIDAD | G38: 0 | H38: m2 | I38: SI CUMPLE | L38: ='CARGA U'!C22 -> 200
F39: NO DONARA A LA MUNICIPALIDAD | G39: 0 | H39: m2
F40: =IF(J25<=250,"NO ESTA SUJETO A CARGAS URBANISTICAS"," ") -> NO ESTA SUJETO A CARGAS URBANISTICAS
F42: EVALUACION DE UBICACIÓN DEL INMUEBLE:
E44: 1 | F44: =IF(FACTIBILIDAD!D20="N/A","No se encuentra en suelo especial de proteccion","Suelo especial de Proteccion Require dictamen de OT/Gestion de Riesgos") -> No se encuentra en suelo especial de proteccion | I44: =IF(F44="No se encuentra en suelo especial de proteccion","SI CUMPLE","NO CUMPLE") -> SI CUMPLE
E45: 2 | F45: =IF(FACTIBILIDAD!D21="N/A","No se encuentra en suelo rural o forestal") -> No se encuentra en suelo rural o forestal | I45: =IF(F45="No se encuentra en suelo rural o forestal","SI CUMPLE","NO CUMPLE") -> SI CUMPLE
E46: 3 | F46: =IF(FACTIBILIDAD!D22="NO","No se encuentra en zona de amenaza de sismo","Requiere dictamen de OT y CONRED") -> No se encuentra en zona de amenaza de sismo | I46: =IF(F46="No se encuentra en zona de amenaza de sismo","SI CUMPLE","NO CUMPLE") -> SI CUMPLE
E47: 4 | F47: =IF(FACTIBILIDAD!D23="NO","No se encuentra en una zona de inundacion","Requiere dictamen de OT y gestion de Riesgos") -> No se encuentra en una zona de inundacion | I47: =IF(F47="No se encuentra en una zona de inundacion","SI CUMPLE","NO CUMPLE") -> SI CUMPLE
E48: 5 | F48: =IF(FACTIBILIDAD!D24="NO","Area fuera de amenaza por deslizamiento","Requiere dictamen de OT y Gestion de Riesgos") -> Area fuera de amenaza por deslizamiento | I48: =IF(F48="Area fuera de amenaza por deslizamiento","SI CUMPLE","NO CUMPLE") -> SI CUMPLE
E49: 6 | F49: =IF(FACTIBILIDAD!D25="NO","No se encuentra en area de proyecto urbano",FACTIBILIDAD!D26) -> No se encuentra en area de proyecto urbano | I49: =IF(F49="No se encuentra en area de proyecto urbano","SI CUMPLE","NO CUMPLE") -> SI CUMPLE
E50: 7 | F50: =IF(FACTIBILIDAD!D27="NO","No se encuentra en Centro Historico y/o monumento aislado","Se encuentra en centro Historico") -> No se encuentra en Centro Historico y/o monumento aislado | I50: =IF(F50="No se encuentra en Centro Historico y/o monumento aislado","SI CUMPLE","NO CUMPLE") -> SI CUMPLE
E51: 8 | F51: =IF(FACTIBILIDAD!D28="NO","No se encuentra en sector sujeto a Plan Parcial","Se encuentra en sector Sujeto a Plan Parcial") -> No se encuentra en sector sujeto a Plan Parcial | I51: =IF(F51="No se encuentra en sector sujeto a Plan Parcial","SI CUMPLE","NO CUMPLE") -> SI CUMPLE
F53: EN EL INFORME DE FACTIBILIDAD SE EVALUA ÚNICAMENTE LO CORRESPONDIENTE A LOS MAPAS ESTABLECIDOS EN EL PLAN DE ORDENAMIENTO TERRITORIAL, SI EXISTIERE UNA CONDICIÓN DE RIESGO DENTRO O CERCA DEL INMUEBLE, LA CONDICIÓN A LA QUE SE ENCUENTRE SUJETA SERÁ EVALUADA DURANTE EL PROCESO DEL EXPEDIENTE DE LICENCIA DE CONSTRUCCIÓN, SEGUN SEA EL CASO.
F56: EVALUACIÓN VIAL PRELIMINAR Y PARQUEOS
F58: DESCRIPCION FINAL: | I58: VIAS | J58: ANCHO (m) | K58: ACERA | L58: VIA ACTUAL
F59: Proyecto: | G59: =FACTIBILIDAD!C2 -> BAJO IMPACTO | I59: =IF(FACTIBILIDAD!E68=0,"",FACTIBILIDAD!E68) -> V3 | J59: =IFERROR(LOOKUP(I59,tabla!$AB$4:$AB$11,tabla!$AC$4:$AC$11),"") -> 15.5 | K59: =IFERROR(LOOKUP(I59,tabla!$AB$4:$AB$11,tabla!$AD$4:$AD$11),"") -> 4 | L59: =IF(FACTIBILIDAD!E73=0,"",FACTIBILIDAD!E73)
G60: =IF(FACTIBILIDAD!D59=100%,"RESIDENCIAL", "MIXTO") -> RESIDENCIAL | I60: =IF(FACTIBILIDAD!E69=0,"",FACTIBILIDAD!E69) | J60: =IFERROR(LOOKUP(I60,tabla!$AB$4:$AB$11,tabla!$AC$4:$AC$11),"") | K60: =IFERROR(LOOKUP(I60,tabla!$AB$4:$AB$11,tabla!$AD$4:$AD$11),"") | L60: =IF(FACTIBILIDAD!E74=0,"",FACTIBILIDAD!E74)
I61: =IF(FACTIBILIDAD!E70=0,"",FACTIBILIDAD!E70) | J61: =IFERROR(LOOKUP(I61,tabla!$AB$4:$AB$11,tabla!$AC$4:$AC$11),"") | K61: =IFERROR(LOOKUP(I61,tabla!$AB$4:$AB$11,tabla!$AD$4:$AD$11),"") | L61: =IF(FACTIBILIDAD!E75=0,"",FACTIBILIDAD!E75)
I62: =IF(FACTIBILIDAD!E71=0,"",FACTIBILIDAD!E71) | J62: =IFERROR(LOOKUP(I62,tabla!$AB$4:$AB$11,tabla!$AC$4:$AC$11),"") | K62: =IFERROR(LOOKUP(I62,tabla!$AB$4:$AB$11,tabla!$AD$4:$AD$11),"") | L62: =IF(FACTIBILIDAD!E76=0,"",FACTIBILIDAD!E76)
F64: PARQUEOS: 1 PARQUEO VEHICULAR
F65: 1. El calculo de dotacion y diseño de estacionamiento debe apegarse a los parametros establecidos en el Articulo 39 del Plan de Ordenamiento Territorial
F66: 2. El uso de parqueos corresponde únicamente al uso del inmueble presentado, si se da un cambio en el uso del inmueble debe ajustarse a los parametros establecidos.
F67: DESCRIPCION DEL USO DEL SUELO DEL PROYECTO
F69: USO DE SUELO 1 | G69: =FACTIBILIDAD!F49 -> RESIDENCIAL | J69: =IF(FACTIBILIDAD!D49=0,"",FACTIBILIDAD!D49) -> 66666 | K69: m2
F70: USO DE SUELO 2 | G70: =IF(FACTIBILIDAD!F50=0,"",FACTIBILIDAD!F50) | J70: =IF(FACTIBILIDAD!D50=0,"",FACTIBILIDAD!D50) | K70: m2
F71: USO DE SUELO 3 | G71: =IF(FACTIBILIDAD!F51=0,"",FACTIBILIDAD!F51) | J71: =IF(FACTIBILIDAD!D51=0,"",FACTIBILIDAD!D51) | K71: m2
F72: USO DE SUELO 4 | G72: =IF(FACTIBILIDAD!F52=0,"") | J72: =IF(FACTIBILIDAD!D52=0,"",FACTIBILIDAD!D52) | K72: m2
F74: Resolución de Ordenamiento Territorial No.
F76: OBSERVACIONES DEL PROYECTO
F77: 1. Deben de cumplirse con todos los requisitos correspondientes al proyecto para la solicitud de la licencia de construcción, debiendo cumplir con las dimensiones minimas establecidas en el articulo 85 del Plan de Ordenamiento Territorial.
F78: 2
F79: 3
F80: 4
F81: EL INFRASCRITO JEFE DEL DEPARTAMENTO DE CONTROL DE OBRAS CERTIFICA:
F82: Que en fecha | G82: =G14 -> 46180 | I82: se efectuó el informe de factibilidad en base al expediente registrado número
F83: =G11 -> RPNC1-4240426 | G83: a nombre de | I83: =G12 -> CAJAS ITZEP, RAFAEL SALVADOR | K83: y factura Numero
G84: para el inmueble ubicado en | J84: =G13 -> 8va AVENIDA 0-10
F85: El proyecto es considerado | G85: FACTIBLE debido a que CUMPLE con lo establecido en el Plan de Ordenamiento Territorial.
F87: LA CERTIFICACIÓN DE FACTIBILIDAD NO CONSTITUYE UNA LICENCIA DE OBRA
F88: Cualquier modificación a la planificación presentada dejará sin efecto la factibilidad del proyecto, a su vez se indica que la emisión de una nueva factibilidad para un inmueble en especifico deja sin validez la anterior siendo la mas reciente la factibilidad válida siempre y cuando la misma se encuentre vigente.
G142: FACTIBLE debido a que CUMPLE con lo establecido en el Plan de Ordenamiento Territorial.
G143: NO FACTIBLE debido a que NO CUMPLE con lo establecido en el Plan de Ordenamiento Territorial.

Sheet CARGA U
E2: TOTAL DE CARGA A DONAR (M2) | F2: =ROUND((((100000*2.6/-(0.000085*POWER((C4*3-1),5)+13))+25000)/100000)*C$3,2) -> 0
A3: 1 | B3: INGRESA AREA DEL PROYECTO | C3: 0 | E3: =F4 -> 0 | F3: =IF((C6="NO"),(F2*1.3),F2) -> 0 | AS3: SI
A4: 2 | B4: INDICE DE EDIFICABILIDAD SOLO 1 DECIMAL | C4: 0 | F4: =ROUND(IF(C5="SI",F3*0.85,F3), 2) -> 0 | AS4: NO
A5: 3 | B5: VA A DONAR | C5: NO
A6: 4 | B6: CUMPLE CON EL USO MIXTO | C6: SI
B19: % permeabilidad según sector | C19: 0
B20: Area construcción (huella) | C20: =+FACTIBILIDAD!D35 -> 200 | D20: m2
B21: Area permeable | C21: =+(C19*C20)/(1-C19) -> 0 | D21: m2
B22: AREA TOTAL PROYECTO | C22: =+C20+C21 -> 200 | D22: m2

Sheet CATEGORIZACION DE UDS
G4: CERTIFICACIÓN DE CATEGORIZACIÓN DE USO DE SUELO
G6: Vigencia 6 meses a partir de la fecha de emisión
F9: DATOS DEL EXPEDIENTE:
F11: EXPEDIENTE | G11: =FACTIBILIDAD!D11 -> RPNC1-4240426
F12: NOMBRE | G12: =FACTIBILIDAD!D9 -> CAJAS ITZEP, RAFAEL SALVADOR
F13: DIRECCION | G13: =FACTIBILIDAD!D10 -> 8va AVENIDA 0-10
F14: FECHA | G14: =FACTIBILIDAD!D8 -> 46180
F15: NOMBRE DEL PROYECTO | G15: =FACTIBILIDAD!D12 -> UNIFAMILIAR
F16: FINCA | G16: =FACTIBILIDAD!D13 -> F
F17: FOLIO | G17: =FACTIBILIDAD!D14 -> FOL
F18: LIBRO | G18: =FACTIBILIDAD!D15 -> LIB
F20: CLASIFICACIÓN DEL SUELO
K21: % | L21: m2
F22: 1 | G22: =FACTIBILIDAD!D19 -> URBANO Q2 (URB-Q2)
F23: 2
F24: 3
F26: RECTIFICACIÓN DE SECTOR DE USO DE SUELO
G28: RESOLUCION DE ORDENAMIENTO TERRITORIAL No.
F31: CONSIDERACIONES SEGÚN RESOLUCIÓN DE ORDENAMIENTO TERRITORIAL | G31: 1
G32: 2
G33: 3
F38: EL INFRASCRITO JEFE DEL DEPARTAMENTO DE CONTROL DE OBRAS CERTIFICA:
F39: Que en fecha | G39: =G14 -> 46180 | I39: se efectuó el informe de categorización de uso de suelo en base al expediente
F40: =G11 -> RPNC1-4240426 | G40: a nombre de | I40: =G12 -> CAJAS ITZEP, RAFAEL SALVADOR | K40: y factura Numero
F41: XXXXXXX | G41: para el inmueble ubicado en | J41: =G13 -> 8va AVENIDA 0-10
F42: haciendo constar que los datos anteriormente descritos podrán ser utilizados para la evaluación de proyectos siempre que se tomen
F43: las consideraciones establecidas para cada sector.
F44: LA CERTIFICACIÓN DE CATEGORIZACIÓN DE USO DE SUELO NO CONSTITUYE UNA LICENCIA DE CONSTRUCCIÓN Y/O DE USO DE SUELO

Sheet C. NOTIFICACION
D11: CEDULA DE NOTIFICACION
O13: CALCULO DE MULTAS
A14: No. | L14: DESCRIPCION | N14: C/ METRO | R14: PAGO
L15: INDICE DE EDIFICABILIDAD | N15: 100 | O15: ='FORMATO FACT'!J35-'FORMATO FACT'!G35 -> 66026 | Q15: =N15*O15 -> 6602600 | R15: =IF((Q15)<0,0,Q15) -> 6602600
A16: EXPEDIENTE No. | D16: =FACTIBILIDAD!D11 -> RPNC1-4240426 | L16: AREA PERMEABLE | N16: 100 | O16: =IF(FACTIBILIDAD!D39>'FORMATO FACT'!G30*'FORMATO FACT'!J25,0,'FORMATO FACT'!G30*'FORMATO FACT'!J25-FACTIBILIDAD!D39)*N16 -> 0 | R16: =O16 -> 0
L17: ALTURA DE BLOQUE | N17: 100 | O17: =IF('FORMATO FACT'!J28-'FORMATO FACT'!G28<0,0,'FORMATO FACT'!J28-'FORMATO FACT'!G28) -> 0 | Q17: =N17*O17 -> 0 | R17: =IF((Q17)<0,0,Q17) -> 0
L18: INGRESAR COSTO DE LICENCIA | R18: 504.14
M19: AREA PERMEABLE FINAL | N19: AREA QUE CUMPLE | R19: =SUM(R15:R18) -> 6603104.1
A20: En la ciudad de Quetzaltenango en Fecha | H20: siendo las | P20: TOTAL | Q20: 0.25 | R20: =R19*Q20 -> 1650776
A21: ubicados en el Departamento de Control de Obras. Se le notifica sobre la multa impuesta por la infraccion
A22: al Plan de Ordenamiento Territorial en el artículo 123 inciso b. y p. Por lo que tendrá que efectuar el pago
A23: por la cantidad de | D23: =R20 -> 1650776 | E23: correspondiente al 25% del valor de la licencia de construccion al solicitar
A24: =FACTIBILIDAD!D12 -> UNIFAMILIAR | F24: , del expediente a nombre de | I24: =FACTIBILIDAD!D9 -> CAJAS ITZEP, RAFAEL SALVADOR
A25: por medio de la cedula de notificacion que entrego a
A26: quien se identifica con No. De CUI | H26: quien se da por enterado y firma la presente.
E32: F.
A35: En su derecho de defensa, se le otorgan cinco dias Habiles para presentar su inconformidad por el escrito.

Sheet tabla
H1: Parámetros de fraccionamientos | J1: Parámetros de obra | T1: Parámetros de uso del suelo
J2: Índice de edificabilidad | L2: Porcentaje de permeabilidad | M2: Bloque inferior | P2: Bloque superior | S2: Altura
B3: BASE | C3: AMPLIADO | H3: Superficie de predio | I3: Frente de predio | J3: Base | K3: Ampliado | M3: Altura | N3: Separación a colindancia | O3: Lado mínimo de patio y pozos de luz | P3: Altura | Q3: Separación a colindancia | R3: Lado mínimo de patio y pozos de luz | T3: Parámetro de uso del suelo mixto | U3: Máximo de usos del suelo no residenciales ordinarios | AC3: ancho total | AD3: acera
A4: 1 | B4: 2.7 | C4: 4 | D4: 500 | E4: 0.1 | G4: URBANO Q1 (URB-Q1) | H4: 500 | I4: 15 | J4: 0 | K4: 3.2 | L4: 0.1 | M4: 18 | N4: 0 | O4: 0.25 | P4: 51 | Q4: 3 | R4: 0.125 | S4: 33 | T4: 0.2 | U4: 5000 | V4: 2.7 | W4: 4 | AB4: VR | AC4: 50 | AD4: 7
A5: 2 | B5: 2.3 | C5: 3.5 | D5: 400 | E5: 0.1 | G5: URBANO Q2 (URB-Q2) | H5: 400 | I5: 15 | J5: 0 | K5: 3.2 | L5: 0.1 | M5: 18 | N5: 0 | O5: 0.25 | P5: 47 | Q5: 3 | R5: 0.125 | S5: 29 | T5: 0.3 | U5: 3000 | V5: 2.3 | W5: 3.5 | AB5: V1 | AC5: 30 | AD5: 5
A6: 3 | B6: 2 | C6: 3 | D6: 300 | E6: 0.15 | G6: URBANO Q3 (URB-Q3) | H6: 300 | I6: 10 | J6: 0 | K6: 2.6 | L6: 0.15 | M6: 15 | N6: 0 | O6: 0.25 | P6: 44 | Q6: 3 | R6: 0.125 | S6: 29 | T6: 0.4 | U6: 1500 | V6: 2 | W6: 3 | AB6: V2 | AC6: 20 | AD6: 3
A7: 4 | B7: 1.7 | C7: 2.5 | D7: 150 | E7: 0.15 | G7: URBANO Q4 (URB-Q4) | H7: 150 | I7: 6 | J7: 0 | K7: 2.2 | L7: 0.15 | M7: 11 | N7: 0 | O7: 0.25 | P7: 29 | Q7: 3 | R7: 0.125 | S7: 18 | T7: 0.5 | U7: 500 | V7: 1.7 | W7: 2.5 | AB7: V3 | AC7: 15.5 | AD7: 4
A8: 5 | B8: 1.4 | C8: 2 | D8: 100 | E8: 0.3 | G8: URBANO Q5 (URB-Q5) | H8: 100 | I8: 5 | J8: 0 | K8: 1.8 | L8: 0.15 | M8: 11 | N8: 0 | O8: 0.25 | P8: 26 | Q8: 3 | R8: 0.125 | S8: 15 | T8: 0.6 | U8: 500 | V8: 1.4 | W8: 2 | AB8: V4 | AC8: 13.5 | AD8: 3
A9: 6 | B9: 1 | C9: 0 | D9: 100 o mas | E9: 0.4 | G9: URBANO Q6 (URB-Q6) | H9: 100 | I9: 5 | J9: 0 | K9: 1.5 | L9: 0.4 | M9: 8 | N9: 0 | O9: 0.25 | P9: 16 | Q9: 3 | R9: 0.125 | S9: 8 | T9: 0.75 | U9: 250 | V9: 1 | W9: 0 | AB9: V5 | AC9: 9 | AD9: 1.5
A10: 7 | B10: 0.5 | C10: 0 | D10: 436.81 | E10: 0.6 | G10: URBANO Q7 (URB-Q7) | H10: 200 | I10: 6 | J10: 0 | K10: 0.8 | L10: 0.6 | M10: 6 | N10: 0 | O10: 0.25 | P10: 14 | Q10: 3 | R10: 0.125 | S10: 8 | T10: 0.8 | U10: 100 | V10: 0.5 | W10: 0 | AB10: Cicloruta | AC10: 2
A11: QPRO | B11: 0.5 | C11: 0 | D11: 436.81 | E11: 0.65 | G11: URBANO PROTECCION NATURAL (URB-PRO) | H11: 400 | I11: 15 | J11: 0 | K11: 0.7 | L11: 0.65 | M11: 6 | N11: 0 | O11: 0.25 | P11: 6 | Q11: - | R11: - | S11: - | T11: 0.8 | U11: RESTRICCIÓN | V11: 0.5 | W11: 0 | AB11: vias peatonales | AC11: 3
A12: ESPECIAL | G12: ESPECIAL
I13: SI CUMPLE | L13: BAJO IMPACTO
I14: NO CUMPLE | L14: ALTO IMPACTO
A15: RUR-AGR-CL | E15: BASE
A16: RUR-AGR-SL | E16: AMPLIADO
A17: RUR-NUR | E17: INGRESO DE NUEVO IE
A18: ESPECIAL DE PROTECCION
A19: FOR-SIGAP
A20: FOR-PRD
A21: FOR-CO
A22: FOR-REE
A23: FOR-RCN
A24: LIMITE DE ALDEAS Y CANTONES
A25: N/A
A27: SI
A28: NO
A30: CENTRO HISTORICO
A31: CORREDOR CENTRAL
... A67: N/A
E68: RESIDENCIAL
A69: RESIDENCIAL | G69: Ordinarios | I69: Condicionados
A70: NO_RESIDENCIAL_ORD | G70: Venta de productos y prestacion de servicios | I70: Estacionamiento de vehiculos livianos
A71: NO_RESIDENCIAL_COND | G71: consumo de comidas y bebidas | I71: Almacenamiento, logistica, embalaje u otras activides relacionadas con el transporte pesado
G72: labores de oficina | I72: Servicios de publicidad o promocion
G73: enseñanza | I73: Enseñanza superior
G74: espectadores sentados | I74: Manejo de residuos biologicos, medicos u hospitalarios
G75: campo o canchas deportivas | I75: actividades masivas de excavacion, procesamiento, o deposito de materiales
G76: produccion, reparacion, almacenamiento de productos | I76: Almacenamiento o expendio de sustancias toxicas, combustibles
G77: alojamiento o encamamiento | I77: actividades relacionadas con el movimiento masivo de pasajeros
G78: recreacion individuales o grupales | I78: Servicio de manejo, almacenaje, procesamiento o disposicion de desechos solidos
G79: ocio enstanciales | I79: produccion y distribucion de productos o servicios publicos
G80: Estacionamiento de vehiculos livianos | I80: actividades con autoservicio
G81: Almacenamiento, logistica, embalaje u otras activides relacionadas con el transporte pesado | I81: consumo de bebidas alcoholicas
G82: Servicios de publicidad o promocion | I82: actividades grupales, de espectaculos en vivo o que produzcan aglomeracion de personas
G83: Enseñanza superior | I83: utilizacion de instrumentos musicales o de aparatos reproductores o amplificadores de sonido
... G90: actividades con autoservicio | I90: actividades relacionadas al comercio o servicio sexual
G91: consumo de bebidas alcoholicas
G92: actividades grupales, de espectaculos en vivo o que produzcan aglomeracion de personas
G93: utilizacion de instrumentos musicales o de aparatos reproductores o amplificadores de sonido
G94: celebracion de servicios religiosos y realizacion de actividades conexas
G95: Servicios de reparacion, mantenimiento o limpieza de vehiculos y otros objetos mayores
G96: actividades de manufactura o industria mecanizada o automatizada
G97: servicio de alojamiento con tarifa por fraccion de tiempo
G98: actividades de velacion , embalsamiento, enterramiento, inhumacion, o cremacion de restos humanos y animales
G99: realizacion de juegos pasivos o de apuestas debidamente autorizados
G100: actividades relacionadas al comercio o servicio sexual

Sheet PREGUNTAS
B1: permeabilidad sobre area efectiva (el pot no lo menciona) al contrario solo dice superficie del predio
B2: indice de edificabilidad para cada proyecto? Como se calcula con cuantos decimales
B3: la mixtura del proyecto solo es sobre area sobre la superficie sin sotanos el pot no lo menciona
B4: se puede pedir doble cesion de area xqe según el pot
B5: en el pot menciona qe el informe de fact es requisito de licencia de construccion
B6: las zonas sismicas como las vamos a trabajar estamos seguros de ese estudio, se tomaron en cuenta las zonificaciones de fallas, se prohiben licencias en ese lugar o esta afecto a estudio
B7: para condominios menciona en el articulo
B8: menores a 250 m2 todos estan afectos a cargas urbanisticas a pesar de no ser vivienda??
B9: se tomo en cuenta los retiros de los bloques para viviendas?????
B10: se pedira doble cesion, la carga urbanistica no corresponde a el area de calles?????
B11: Que se hace en los caso donde ya existe construccion
B12: superficie de construccion
